stl/__init__.py
stl/stl.py
py_signal_temporal_logic-0.1.1.dist-info/LICENSE
py_signal_temporal_logic-0.1.1.dist-info/WHEEL
py_signal_temporal_logic-0.1.1.dist-info/METADATA
py_signal_temporal_logic-0.1.1.dist-info/RECORD
